pyquesta/__init__.py
pyquesta/pyquesta.py
pyquesta/dpi/sv_conduit.c
pyquesta/dpi/sv_conduit.h
pyquesta/makefiles/pyquesta.mk
pyquesta-2.5.1.data/scripts/gen_svconduit_pkgs
pyquesta-2.5.1.data/scripts/pyquesta-config
pyquesta-2.5.1.dist-info/LICENSE
pyquesta-2.5.1.dist-info/METADATA
pyquesta-2.5.1.dist-info/WHEEL
pyquesta-2.5.1.dist-info/top_level.txt
pyquesta-2.5.1.dist-info/RECORD
