Metadata-Version: 2.1
Name: pyquesta
Version: 2.5.1
Summary: A link between Questa and Python
Author: Ray Salemi
Author-email: ray.raysalemi@siemens.com
License: Siemens Universal Customer Agreement
Requires-Python: >=3.6
Requires-Dist: cocotb (>=1.6.0)
Requires-Dist: protlib
Requires-Dist: pyyaml
